Metadata-Version: 2.1
Name: permissive-slugify
Version: 1.0.0
Summary: Fork of un33k/python-slugify to fix issue #68
Home-page: https://github.com/roniemartinez/permissive-slugify
Author: Ronie Martinez
Author-email: ronmarti18@gmail.com
License: MIT
Download-URL: https://github.com/roniemartinez/permissive-slugify/tarball/1.0.0
Platform: UNKNOWN
Classifier: Development Status :: 5 - Production/Stable
Classifier: Intended Audience :: Developers
Classifier: License :: OSI Approved :: MIT License
Classifier: Operating System :: OS Independent
Classifier: Programming Language :: Python :: 2
Classifier: Programming Language :: Python :: 2.7
Classifier: Programming Language :: Python :: 3
Classifier: Programming Language :: Python :: 3.4
Classifier: Programming Language :: Python :: 3.5
Classifier: Programming Language :: Python :: 3.6
Classifier: Programming Language :: Python :: 3.7
Classifier: Programming Language :: Python :: Implementation :: CPython
Provides-Extra: text-unidecode
Provides-Extra: unidecode
